LICENSE
safebag/__init__.py
safebag/_chain_proxy.py
safebag/_methods.py
safebag-0.2.0.dist-info/LICENSE
safebag-0.2.0.dist-info/WHEEL
safebag-0.2.0.dist-info/METADATA
safebag-0.2.0.dist-info/RECORD
