Metadata-Version: 2.1
Name: safebag
Version: 0.2.0
Summary: Little python package implementing optional chaining
Home-page: https://github.com/galeNightIn/safebag
License: MIT
Author: Alexandr Solovev
Author-email: nightingale.alex.info@gmail.com
Requires-Python: >=3.7,<4.0
Classifier: License :: OSI Approved :: MIT License
Classifier: Programming Language :: Python :: 3
Classifier: Programming Language :: Python :: 3.10
Classifier: Programming Language :: Python :: 3.7
Classifier: Programming Language :: Python :: 3.8
Classifier: Programming Language :: Python :: 3.9
Project-URL: Repository, https://github.com/galeNightIn/safebag
